[
    {
    "_id": "691a31df60d7dc8085af06dc",
    "date": "2025-11-16 20:19:42.400148",
    "username": "user-rfa",
    "message": "Збереження даних у базі даних MongoDB."
  },

  {
    "_id": "691a341bb43ec0a941bbda3c",
    "date": "2025-11-16 20:29:15.712511",
    "username": "user-rfa",
    "message": "Створення записів у форматі, що має значення для реального застосування."
  },

  {
    "_id": "691a3449b43ec0a941bbda3d",
    "date": "2025-11-16 20:30:01.276759",
    "username": "user-rfa",
    "message": "Використання протоколу UDP або TCP для взаємодії між вебдодатком і сервером."
  }
]